{
  "name": "Ohrmleaveentitlement",
  "settings": {
    "strict": false,
    "forceId": false,
    "replaceOnPUT": true,
    "idInjection": false,
    "mysql": {
      "schema": "orangehrm",
      "table": "ohrmleaveentitlement"
    }
  },
  "properties": {
    "createdbyid": {
      "type": "number",
      "required": false,
      "length": null,
      "precision": 10,
      "scale": 0,
      "mysql": {
        "columnName": "createdById",
        "dataType": "int",
        "dataLength": null,
        "dataPrecision": 10,
        "dataScale": 0,
        "nullable": "Y"
      }
    },
    "createdbyname": {
      "type": "string",
      "required": false,
      "length": 255,
      "precision": null,
      "scale": null,
      "mysql": {
        "columnName": "createdByName",
        "dataType": "varchar",
        "dataLength": 255,
        "dataPrecision": null,
        "dataScale": null,
        "nullable": "Y"
      }
    },
    "crediteddate": {
      "type": "date",
      "required": false,
      "length": null,
      "precision": null,
      "scale": null,
      "mysql": {
        "columnName": "creditedDate",
        "dataType": "datetime",
        "dataLength": null,
        "dataPrecision": null,
        "dataScale": null,
        "nullable": "Y"
      }
    },
    "daysused": {
      "type": "string",
      "required": true,
      "length": null,
      "precision": 8,
      "scale": 4,
      "mysql": {
        "columnName": "daysUsed",
        "dataType": "decimal",
        "dataLength": null,
        "dataPrecision": 8,
        "dataScale": 4,
        "nullable": "N"
      }
    },
    "deleted": {
      "type": "number",
      "required": true,
      "length": null,
      "precision": 3,
      "scale": 0,
      "mysql": {
        "columnName": "deleted",
        "dataType": "tinyint",
        "dataLength": null,
        "dataPrecision": 3,
        "dataScale": 0,
        "nullable": "N"
      }
    },
    "empnumber": {
      "type": "number",
      "required": true,
      "length": null,
      "precision": 10,
      "scale": 0,
      "mysql": {
        "columnName": "empNumber",
        "dataType": "int",
        "dataLength": null,
        "dataPrecision": 10,
        "dataScale": 0,
        "nullable": "N"
      }
    },
    "entitlementtype": {
      "type": "number",
      "required": true,
      "length": null,
      "precision": 10,
      "scale": 0,
      "mysql": {
        "columnName": "entitlementType",
        "dataType": "int",
        "dataLength": null,
        "dataPrecision": 10,
        "dataScale": 0,
        "nullable": "N"
      }
    },
    "fromdate": {
      "type": "date",
      "required": true,
      "length": null,
      "precision": null,
      "scale": null,
      "mysql": {
        "columnName": "fromDate",
        "dataType": "datetime",
        "dataLength": null,
        "dataPrecision": null,
        "dataScale": null,
        "nullable": "N"
      }
    },
    "id": {
      "type": "number",
      "id": 1,
      "required": true,
      "length": null,
      "precision": 10,
      "scale": 0,
      "mysql": {
        "columnName": "id",
        "dataType": "int",
        "dataLength": null,
        "dataPrecision": 10,
        "dataScale": 0,
        "nullable": "N"
      },
      "updateOnly": false
    },
    "leavetypeid": {
      "type": "number",
      "required": true,
      "length": null,
      "precision": 10,
      "scale": 0,
      "mysql": {
        "columnName": "leaveTypeId",
        "dataType": "int",
        "dataLength": null,
        "dataPrecision": 10,
        "dataScale": 0,
        "nullable": "N"
      }
    },
    "noofdays": {
      "type": "string",
      "required": true,
      "length": null,
      "precision": 19,
      "scale": 15,
      "mysql": {
        "columnName": "noOfDays",
        "dataType": "decimal",
        "dataLength": null,
        "dataPrecision": 19,
        "dataScale": 15,
        "nullable": "N"
      }
    },
    "note": {
      "type": "string",
      "required": false,
      "length": 255,
      "precision": null,
      "scale": null,
      "mysql": {
        "columnName": "note",
        "dataType": "varchar",
        "dataLength": 255,
        "dataPrecision": null,
        "dataScale": null,
        "nullable": "Y"
      }
    },
    "todate": {
      "type": "date",
      "required": false,
      "length": null,
      "precision": null,
      "scale": null,
      "mysql": {
        "columnName": "toDate",
        "dataType": "datetime",
        "dataLength": null,
        "dataPrecision": null,
        "dataScale": null,
        "nullable": "Y"
      }
    }
  },
  "validations": [],
  "relations": {},
  "acls": [],
  "methods": {}
}
